{
  "/_not-found/page": "app/_not-found/page.js",
  "/about/page": "app/about/page.js",
  "/admin-setup/page": "app/admin-setup/page.js",
  "/admin/analytics/page": "app/admin/analytics/page.js",
  "/admin/activity/page": "app/admin/activity/page.js",
  "/admin/appeals/[id]/page": "app/admin/appeals/[id]/page.js",
  "/admin/appeals/page": "app/admin/appeals/page.js",
  "/admin/fix-users/page": "app/admin/fix-users/page.js",
  "/admin/migrate-creator-names/page": "app/admin/migrate-creator-names/page.js",
  "/admin/moderators/page": "app/admin/moderators/page.js",
  "/admin/petitions/[id]/page": "app/admin/petitions/[id]/page.js",
  "/admin/page": "app/admin/page.js",
  "/admin/petitions/page": "app/admin/petitions/page.js",
  "/admin/users/[id]/page": "app/admin/users/[id]/page.js",
  "/api/appeals/[id]/reply/route": "app/api/appeals/[id]/reply/route.js",
  "/api/appeals/[id]/status/route": "app/api/appeals/[id]/status/route.js",
  "/api/appeals/create/route": "app/api/appeals/create/route.js",
  "/admin/users/page": "app/admin/users/page.js",
  "/api/check-smtp/route": "app/api/check-smtp/route.js",
  "/api/contact/route": "app/api/contact/route.js",
  "/api/email/milestone/route": "app/api/email/milestone/route.js",
  "/api/email/petition-update/route": "app/api/email/petition-update/route.js",
  "/api/email/petition-approved/route": "app/api/email/petition-approved/route.js",
  "/api/email/send/route": "app/api/email/send/route.js",
  "/api/email/signature-confirmation/route": "app/api/email/signature-confirmation/route.js",
  "/api/health/route": "app/api/health/route.js",
  "/api/email/welcome/route": "app/api/email/welcome/route.js",
  "/api/petitions/[code]/route": "app/api/petitions/[code]/route.js",
  "/api/push/send/route": "app/api/push/send/route.js",
  "/api/test-contact/route": "app/api/test-contact/route.js",
  "/api/test-env/route": "app/api/test-env/route.js",
  "/api/whatsapp/send-verification/route": "app/api/whatsapp/send-verification/route.js",
  "/api/verify-recaptcha/route": "app/api/verify-recaptcha/route.js",
  "/api/whatsapp/verify-code/route": "app/api/whatsapp/verify-code/route.js",
  "/api/whatsapp/webhook/route": "app/api/whatsapp/webhook/route.js",
  "/auth/forgot-password/page": "app/auth/forgot-password/page.js",
  "/auth/login/page": "app/auth/login/page.js",
  "/auth/register/page": "app/auth/register/page.js",
  "/auth/verify-email/page": "app/auth/verify-email/page.js",
  "/dashboard/analytics/[id]/page": "app/dashboard/analytics/[id]/page.js",
  "/dashboard/page": "app/dashboard/page.js",
  "/cookies/page": "app/cookies/page.js",
  "/help/page": "app/help/page.js",
  "/moderator/page": "app/moderator/page.js",
  "/contact/page": "app/contact/page.js",
  "/page": "app/page.js",
  "/dashboard/appeals/[id]/page": "app/dashboard/appeals/[id]/page.js",
  "/pricing/page": "app/pricing/page.js",
  "/profile/page": "app/profile/page.js",
  "/test-phone/page": "app/test-phone/page.js",
  "/test-phone-simple/page": "app/test-phone-simple/page.js",
  "/api/appeals/[id]/export/route": "app/api/appeals/[id]/export/route.js",
  "/api/appeals/[id]/route": "app/api/appeals/[id]/route.js",
  "/api/appeals/route": "app/api/appeals/route.js",
  "/guidelines/page": "app/guidelines/page.js",
  "/privacy/page": "app/privacy/page.js",
  "/terms/page": "app/terms/page.js",
  "/petitions/create/page": "app/petitions/create/page.js",
  "/petitions/[id]/edit/page": "app/petitions/[id]/edit/page.js",
  "/petitions/page": "app/petitions/page.js",
  "/petitions/[id]/qr/page": "app/petitions/[id]/qr/page.js",
  "/petitions/[id]/page": "app/petitions/[id]/page.js",
  "/petitions/success/page": "app/petitions/success/page.js"
}